README.md
setup.cfg
setup.py
dragoman/__init__.py
dragoman/core/__init__.py
dragoman/core/axis.py
dragoman/core/binneddata.py
dragoman/core/edges.py
dragoman/core/grid.py
dragoman/core/gridarray.py
dragoman/core/griddata.py
dragoman/core/pointarray.py
dragoman/core/pointdata.py
dragoman/plotting/__init__.py
dragoman/plotting/stat_plot.py
dragoman/translations/__init__.py
dragoman/translations/histogram.py
dragoman/translations/interpolation.py
dragoman/translations/kde.py
dragoman/translations/lookup.py
dragoman/translations/resample.py
dragoman/translations/translation.py
dragoman/utils/__init__.py
dragoman/utils/bind.py
dragoman/utils/formatter.py
dragoman/utils/stats.py
tandem.egg-info/PKG-INFO
tandem.egg-info/SOURCES.txt
tandem.egg-info/dependency_links.txt
tandem.egg-info/requires.txt
tandem.egg-info/top_level.txt