Metadata-Version: 2.1
Name: tandem
Version: 0.4.3
Summary: Look at data in different ways
Home-page: https://github.com/philippeller/dragoman
Author: Philipp Eller
Author-email: peller.phys@gmail.com
License: Apache 2.0
Platform: UNKNOWN
Requires-Python: >=3.6
